testabc/__init__.py
testabc/dictionary.py
testabc/emoji_remover.py
testabc/normalizer.py
testabc/normalizer_utils.py
testabc/regexes/__init__.py
testabc/regexes/currency.py
testabc/regexes/email.py
testabc/regexes/latin.py
testabc/regexes/number.py
testabc/regexes/persian.py
testabc/regexes/phone.py
testabc/regexes/punk.py
testabc/regexes/quote.py
testabc/regexes/url.py
testabc/vidstream/__init__.py
testabc/vidstream/audio.py
testabc/vidstream/streaming.py
khodnevis_normalizer-0.0.2.dist-info/METADATA
khodnevis_normalizer-0.0.2.dist-info/WHEEL
khodnevis_normalizer-0.0.2.dist-info/top_level.txt
khodnevis_normalizer-0.0.2.dist-info/RECORD
