Metadata-Version: 2.1
Name: khodnevis-normalizer
Version: 0.0.2
Summary: Khodnevis Normalizer
Author: khodnevisAI
Author-email: <khodnevis.group@gmail.com>
License: UNKNOWN
Keywords: python,persian,normalizer,text
Platform: UNKNOWN
Classifier: Development Status :: 1 - Planning
Classifier: Intended Audience :: Developers
Classifier: Programming Language :: Python :: 3
Classifier: Operating System :: Unix
Classifier: Operating System :: MacOS :: MacOS X
Classifier: Operating System :: Microsoft :: Windows
Requires-Dist: hazm
Requires-Dist: parsivar
